contextual_encoders/__init__.py
contextual_encoders/aggregator.py
contextual_encoders/computer.py
contextual_encoders/context.py
contextual_encoders/data_utils.py
contextual_encoders/encoder.py
contextual_encoders/gatherer.py
contextual_encoders/inverter.py
contextual_encoders/measure.py
contextual_encoders/reducer.py
LICENSE
contextual_encoders-0.1.1.dist-info/LICENSE
contextual_encoders-0.1.1.dist-info/WHEEL
contextual_encoders-0.1.1.dist-info/METADATA
contextual_encoders-0.1.1.dist-info/RECORD
