Metadata-Version: 2.1
Name: contextual-encoders
Version: 0.1.1
Summary: A library of sklearn compatible contextual categorical variable encoders
Home-page: https://contextual-encoders.readthedocs.io/en/latest/
License: Apache-2.0
Keywords: data-science,machine-learning,scikit-learn
Author: Daniel Fink
Requires-Python: >=3.7,<4.0
Classifier: License :: OSI Approved :: Apache Software License
Classifier: Programming Language :: Python :: 3
Classifier: Programming Language :: Python :: 3.7
Classifier: Programming Language :: Python :: 3.8
Classifier: Programming Language :: Python :: 3.9
Requires-Dist: networkx (>=2.5,<3.0)
Requires-Dist: numpy (>=1.19,<2.0)
Requires-Dist: scikit-learn (>=0.24,<0.25)
Project-URL: Repository, https://github.com/StuttgarterDotNet/contextual-encoders
